lagrange_polynomial/__init__.py
lagrange_polynomial/lagrange_polynomial.py
lagrange_polynomial/py.typed
lagrange_polynomial-0.0.1.dist-info/METADATA
lagrange_polynomial-0.0.1.dist-info/WHEEL
lagrange_polynomial-0.0.1.dist-info/top_level.txt
lagrange_polynomial-0.0.1.dist-info/RECORD
