Metadata-Version: 2.1
Name: lagrange-polynomial
Version: 0.0.1
Summary: Lagrange polynomials over finite fields
Home-page: https://github.com/fionn/lagrange-polynomial
Author: Fionn Fitzmaurice
License: UNKNOWN
Project-URL: Source Code, https://github.com/fionn/lagrange-polynomial
Project-URL: Changelog, https://github.com/fionn/lagrange-polynomial/tags
Project-URL: Documentation, https://github.com/fionn/lagrange-polynomial/blob/master/README.md
Project-URL: Bug Tracker, https://github.com/fionn/lagrange-polynomial/issues
Project-URL: PyPI, https://pypi.org/project/lagrange-polynomial/
Project-URL: Download, https://github.com/fionn/lagrange-polynomial/archive/refs/heads/master.zip
Keywords: lagrange polynomials,interpolation
Platform: UNKNOWN
Classifier: Programming Language :: Python :: 3
Classifier: Development Status :: 4 - Beta
Classifier: Intended Audience :: Developers
Classifier: Topic :: Security :: Cryptography
Classifier: Topic :: Scientific/Engineering :: Mathematics
Classifier: Typing :: Typed
Requires-Python: >=3.9
Provides-Extra: dev
Requires-Dist: pylint ; extra == 'dev'
Requires-Dist: mypy ; extra == 'dev'
Requires-Dist: coverage ; extra == 'dev'
